{"cameraMode":{"drawMode":0,"name":"Shaded","section":"Shading Mode"},"sceneLighting":false,"audioPlay":false,"sceneViewState":{"m_AlwaysRefresh":false,"showFog":true,"showSkybox":false,"showFlares":true,"showImageEffects":true,"showParticleSystems":true,"showVisualEffectGraphs":true,"m_FxEnabled":true},"in2DMode":false,"pivot":{"x":37.76618576049805,"y":38.550270080566409,"z":-56.17930603027344},"rotation":{"x":0.24093295633792878,"y":-0.27962106466293337,"z":0.0727144181728363,"w":0.926546573638916},"size":6.6862473487854,"orthographic":false}